spacexpython/__init__.py
spacexpython/capsules.py
spacexpython/cores.py
spacexpython/crew.py
spacexpython/dragons.py
spacexpython/exceptions.py
spacexpython/history.py
spacexpython/info.py
spacexpython/landingpads.py
spacexpython/launches.py
spacexpython/launchpads.py
spacexpython/missions.py
spacexpython/payloads.py
spacexpython/roadster.py
spacexpython/rockets.py
spacexpython/ships.py
spacexpython/urldata.py
spacexpython/utils.py
test/__init__.py
test/test_capsules.py
test/test_cores.py
test/test_crew.py
test/test_dragons.py
test/test_history.py
test/test_info.py
test/test_landingpads.py
test/test_launches.py
test/test_launchpads.py
test/test_missions.py
test/test_payloads.py
test/test_roadster.py
test/test_rockets.py
test/test_ships.py
test/tutils.py
SpacePY_X-1.1.4.5.dist-info/LICENSE
SpacePY_X-1.1.4.5.dist-info/METADATA
SpacePY_X-1.1.4.5.dist-info/WHEEL
SpacePY_X-1.1.4.5.dist-info/entry_points.txt
SpacePY_X-1.1.4.5.dist-info/top_level.txt
SpacePY_X-1.1.4.5.dist-info/RECORD
