Metadata-Version: 2.1
Name: SpacePY-X
Version: 1.1.4.5
Summary: Simple Python wrapper for the SpaceX API
Home-page: https://github.com/alshapton/SpacePY-X
Author: Andrew Shapton
Author-email: alshapton@gmail.com
License: MIT
Keywords: wrapper api spacex python
Platform: UNKNOWN
Classifier: Programming Language :: Python :: 3
Classifier: License :: OSI Approved :: MIT License
Classifier: Operating System :: OS Independent
Requires-Dist: tinydb
Requires-Dist: beautifulsoup4
Requires-Dist: requests
Requires-Dist: cachepy
